<?xml version="1.0" encoding="UTF-8"?>
<eventPublisher name="fp1" statistics="disable" trace="disable" xmlns="http://wso2.org/carbon/eventpublisher">
  <from streamName="FraudStream" version="1.0.0"/>
  <mapping customMapping="disable" type="text"/>
  <to eventAdapterType="email">
    <property name="email.subject">Unusual request pattern detected</property>
    <property name="email.address">fazlan.pera@gmail.com</property>
    <property name="email.type">text/plain</property>
  </to>
</eventPublisher>
